pip_madison/__init__.py
pip_madison/_cli_util.py
pip_madison/cli.py
pip_madison/utils.py
pip_madison-0.0.6.dist-info/METADATA
pip_madison-0.0.6.dist-info/WHEEL
pip_madison-0.0.6.dist-info/entry_points.txt
pip_madison-0.0.6.dist-info/top_level.txt
pip_madison-0.0.6.dist-info/RECORD
