Metadata-Version: 2.1
Name: pip-madison
Version: 0.0.6
Summary: A simple tool to list available version releases
Home-page: https://github.com/joranbeasley/pip_madison
Author: Joran Beasley
Author-email: joranbeasley@gmail.com
License: UNKNOWN
Platform: UNKNOWN
Classifier: Programming Language :: Python :: 3
Classifier: License :: OSI Approved :: MIT License
Classifier: Operating System :: OS Independent
Requires-Python: >=2.7
Requires-Dist: click
Requires-Dist: bs4
Requires-Dist: requests
Requires-Dist: six
Requires-Dist: pySystem
